Metadata-Version: 1.0
Name: GaussianBinomial-distributions
Version: 1.1
Summary: Gaussian and Binomial distributions
Home-page: UNKNOWN
Author: Jasvir Dhillon
Author-email: jasvirsingh535@gmail.com
License: UNKNOWN
Platform: UNKNOWN
